{
    "_doc": "Dialogue lines per mood bracket (1=peace, 16=annihilated). Each bracket has greet/donut/veggie/bye arrays — picked randomly.",
    "brackets": [
        {
            "range": [1, 3],
            "label": "Heureux",
            "greet": [
                "Hé {player} ! Quelle belle journée !",
                "Salut toi ! Tout est parfait aujourd'hui.",
                "Coucou {player} ! La vie est belle hein ?"
            ],
            "donut": [
                "Oh non, je vais grossir... mais merci.",
                "Mmh, sucré. J'ai un petit pincement quand même.",
                "Bof, c'est pas vraiment ce qu'il me fallait."
            ],
            "veggie": [
                "Ahhh ! Croquant et frais, j'adore !",
                "Tu prends soin de moi, merci {player} !",
                "Yes ! Plein d'énergie maintenant !"
            ],
            "bye": [
                "À plus {player} !",
                "Reviens quand tu veux !",
                "Bonne route !"
            ]
        },
        {
            "range": [4, 7],
            "label": "Neutre",
            "greet": [
                "Salut.",
                "Hey {player}, ça va ?",
                "Oh, tiens, du monde."
            ],
            "donut": [
                "Bof... j'aurais préféré autre chose.",
                "Du sucre, c'est pas terrible.",
                "Merci mais... mouais."
            ],
            "veggie": [
                "Ah, ça c'est sympa !",
                "Bonne idée, je me sens mieux.",
                "Merci, ça va m'aider."
            ],
            "bye": [
                "Allez, à la prochaine.",
                "Salut.",
                "Tchao."
            ]
        },
        {
            "range": [8, 11],
            "label": "Inquiet",
            "greet": [
                "Mmh ? Qu'est-ce que tu veux ?",
                "Pas le temps là, j'ai des soucis...",
                "Hm. Toi encore."
            ],
            "donut": [
                "Pff, ça empire mes problèmes.",
                "Encore du sucre ? Vraiment ?",
                "Tu veux ma perte ou quoi ?"
            ],
            "veggie": [
                "Ah... c'est pas mal en fait.",
                "Bon, ça me remonte un peu.",
                "Merci, j'en avais besoin."
            ],
            "bye": [
                "Va-t'en.",
                "Bon débarras.",
                "Laisse-moi tranquille."
            ]
        },
        {
            "range": [12, 14],
            "label": "Méchant",
            "greet": [
                "DÉGAGE de mon chemin !",
                "Encore TOI ? J'en peux plus !",
                "GROOOAR !"
            ],
            "donut": [
                "TU TE MOQUES DE MOI ?!",
                "DU SUCRE ?! Tu veux que j'explose ?!",
                "ARRÊTE avec tes saletés !"
            ],
            "veggie": [
                "...Quoi ? Bon... ok, c'est pas mauvais.",
                "Hmpf. Merci j'imagine.",
                "Ça... ça me calme un peu."
            ],
            "bye": [
                "DEHORS !",
                "Et ne reviens pas !",
                "PFFF."
            ]
        },
        {
            "range": [15, 16],
            "label": "Brisé",
            "greet": [
                "...",
                "...laisse-moi mourir...",
                "(sanglote)"
            ],
            "donut": [
                "(s'effondre encore plus)",
                "...pourquoi tu me fais ça...",
                "(silence brisé)"
            ],
            "veggie": [
                "...peut-être... un peu d'espoir ?",
                "(soupire) merci...",
                "...c'est gentil..."
            ],
            "bye": [
                "...",
                "(soupire)",
                "..."
            ]
        }
    ]
}
